{
    "homepage": "https://itch.io/docs/butler/",
    "checkver": {
        "url": "https://api.github.com/repos/itchio/butler/tags",
        "jp": "$.[0].name"
    },
    "autoupdate": {
        "url": "https://broth.itch.ovh/butler/windows-amd64/$matchHead/archive/default#/latest.zip"
    },
    "version": "v15.15.0",
    "url": "https://broth.itch.ovh/butler/windows-amd64/15.15.0/archive/default#/latest.zip",
    "bin": "butler.exe",
    "hash": "0d675f90e77663d9593f6620c653a88090bea53440eea239c917650d4ff3c7bf"
}
