{
    "checkver": {
        "github": "https://github.com/pypy-vrc/VRCX"
    },
    "autoupdate": {
        "url": "https://github.com/pypy-vrc/VRCX/releases/download/v$version/VRCX_$cleanVersion.zip"
    },
    "version": "2024.03.23",
    "url": "https://github.com/pypy-vrc/VRCX/releases/download/v2024.03.23/VRCX_20240323.zip",
    "hash": "bb6fcf727f2c710c19d7039f36c76dbd364e15ea4f2b6acdcdf890297ad213b4",
    "shortcuts": [
        [
            "VRCX.exe",
            "VRCX"
        ]
    ]
}
